fund/__init__.py
fund/fund_client.py
fund-0.2.dev0.dist-info/DESCRIPTION.rst
fund-0.2.dev0.dist-info/METADATA
fund-0.2.dev0.dist-info/RECORD
fund-0.2.dev0.dist-info/WHEEL
fund-0.2.dev0.dist-info/entry_points.txt
fund-0.2.dev0.dist-info/metadata.json
fund-0.2.dev0.dist-info/top_level.txt
fund-0.2.dev0.dist-info/zip-safe
