Metadata-Version: 2.0
Name: fund
Version: 0.2.dev0
Summary: 国内基金API接口
Home-page: https://bitbucket.org/yafeile/fund
Author: fly
Author-email: yafeile@sohu.com
License: GPLv3
Keywords: fund
Platform: UNKNOWN
Requires-Dist: msgpack
